MANIFEST.in
setup.py
anthill/profile/__init__.py
anthill/profile/admin.py
anthill/profile/handler.py
anthill/profile/options.py
anthill/profile/server.py
anthill/profile/model/__init__.py
anthill/profile/model/access.py
anthill/profile/model/profile.py
anthill/profile/sql/account_profiles.sql
anthill/profile/sql/gamespace_access.sql
anthill_profile.egg-info/PKG-INFO
anthill_profile.egg-info/SOURCES.txt
anthill_profile.egg-info/dependency_links.txt
anthill_profile.egg-info/namespace_packages.txt
anthill_profile.egg-info/not-zip-safe
anthill_profile.egg-info/requires.txt
anthill_profile.egg-info/top_level.txt