Metadata-Version: 1.0
Name: anthill-profile
Version: 0.2
Summary: User profiles service for Anthill platform
Home-page: https://github.com/anthill-platform/anthill-profile
Author: desertkun
Author-email: desertkun@gmail.com
License: MIT
Platform: UNKNOWN
